odoo/addons/ssi_account_create_liquidity_journal/README.rst
odoo/addons/ssi_account_create_liquidity_journal/__init__.py
odoo/addons/ssi_account_create_liquidity_journal/__manifest__.py
odoo/addons/ssi_account_create_liquidity_journal/security/ir.model.access.csv
odoo/addons/ssi_account_create_liquidity_journal/static/description/icon.png
odoo/addons/ssi_account_create_liquidity_journal/wizards/__init__.py
odoo/addons/ssi_account_create_liquidity_journal/wizards/wizard_create_liquidity_journal.py
odoo/addons/ssi_account_create_liquidity_journal/wizards/wizard_create_liquidity_journal.xml
odoo14_addon_ssi_account_create_liquidity_journal-14.0.1.0.2.dev1.dist-info/METADATA
odoo14_addon_ssi_account_create_liquidity_journal-14.0.1.0.2.dev1.dist-info/WHEEL
odoo14_addon_ssi_account_create_liquidity_journal-14.0.1.0.2.dev1.dist-info/top_level.txt
odoo14_addon_ssi_account_create_liquidity_journal-14.0.1.0.2.dev1.dist-info/RECORD
